odoo/addons/shopinvader_product/README.rst
odoo/addons/shopinvader_product/__init__.py
odoo/addons/shopinvader_product/__manifest__.py
odoo/addons/shopinvader_product/demo/product_attribute_value.xml
odoo/addons/shopinvader_product/demo/product_category.xml
odoo/addons/shopinvader_product/demo/product_product.xml
odoo/addons/shopinvader_product/i18n/shopinvader_product.pot
odoo/addons/shopinvader_product/models/__init__.py
odoo/addons/shopinvader_product/models/category.py
odoo/addons/shopinvader_product/models/product_product.py
odoo/addons/shopinvader_product/models/product_template.py
odoo/addons/shopinvader_product/models/tools.py
odoo/addons/shopinvader_product/readme/CONTRIBUTORS.rst
odoo/addons/shopinvader_product/readme/DESCRIPTION.rst
odoo/addons/shopinvader_product/schemas/__init__.py
odoo/addons/shopinvader_product/schemas/category.py
odoo/addons/shopinvader_product/schemas/product.py
odoo/addons/shopinvader_product/static/description/index.html
odoo/addons/shopinvader_product/tests/__init__.py
odoo/addons/shopinvader_product/tests/test_category_schema.py
odoo/addons/shopinvader_product/tests/test_product.py
odoo/addons/shopinvader_product/views/product_category.xml
odoo/addons/shopinvader_product/views/product_template.xml
odoo_addon_shopinvader_product-16.0.1.0.5.dist-info/METADATA
odoo_addon_shopinvader_product-16.0.1.0.5.dist-info/WHEEL
odoo_addon_shopinvader_product-16.0.1.0.5.dist-info/top_level.txt
odoo_addon_shopinvader_product-16.0.1.0.5.dist-info/RECORD
