Metadata-Version: 2.1
Name: odoo-addon-shopinvader_product
Version: 16.0.1.0.5
Summary: Adds shopinvader product fields and schemas
Home-page: https://github.com/shopinvader/odoo-shopinvader
Author: ACSONE SA/NV
License: AGPL-3
Classifier: Programming Language :: Python
Classifier: Framework :: Odoo
Classifier: Framework :: Odoo :: 16.0
Classifier: License :: OSI Approved :: GNU Affero General Public License v3
Classifier: Development Status :: 3 - Alpha
Requires-Python: >=3.10
Requires-Dist: extendable-pydantic>=1.2.0
Requires-Dist: odoo-addon-extendable<16.1dev,>=16.0dev
Requires-Dist: odoo-addon-pydantic<16.1dev,>=16.0dev
Requires-Dist: odoo<16.1dev,>=16.0a
Requires-Dist: pydantic>=2.0.0
Requires-Dist: unidecode
